LICENSE
MANIFEST.in
NULL.rst
README.rst
dev-requirements.txt
requirements.txt
setup.py
test-requirements.txt
codefurther/__init__.py
codefurther/errors.py
codefurther/helpers.py
codefurther/package_info.json
codefurther/utils.py
codefurther.egg-info/PKG-INFO
codefurther.egg-info/SOURCES.txt
codefurther.egg-info/dependency_links.txt
codefurther.egg-info/requires.txt
codefurther.egg-info/top_level.txt
codefurther/directions/__init__.py
codefurther/directions/directions.py
codefurther/email/__init__.py
codefurther/email/email.py
codefurther/football/__init__.py
codefurther/football/constants.py
codefurther/football/football.py
codefurther/football/models.py
codefurther/lyrics/__init__.py
codefurther/lyrics/lyrics.py
codefurther/slack/__init__.py
codefurther/slack/slack.py
codefurther/textmessage/__init__.py
codefurther/textmessage/textmessage.py
codefurther/top40/__init__.py
codefurther/top40/top40.py
codefurther/twitter/__init__.py
codefurther/twitter/twitter.py
codefurther/weather/__init__.py
codefurther/weather/weather.py
examples/__init__.py
examples/directionsdemo.py
examples/footballdemo1.py
examples/lyricsdemo.py
examples/lyricsdemo2.py
examples/lyricsdemo3.py
examples/lyricsdemo4.py
examples/lyricsdemo5.py
examples/slack.py
examples/sms.py
examples/top40demo.py
examples/top40demo2.py
examples/top40demo3.py
examples/top40demo4.py
examples/top40demo5.py
examples/twitter.py